{
    "prepare_queue": {
        "installed": [],
        "uninstalled": []
    },
    "config_munge": {
        "files": {
            "res/xml/config.xml": {
                "parents": {
                    "/*": [
                        {
                            "xml": "<feature name=\"NotificationHub\"><param name=\"android-package\" value=\"msopentech.azure.NotificationHub\" /></feature>",
                            "count": 1
                        }
                    ]
                }
            },
            "AndroidManifest.xml": {
                "parents": {
                    "/*": [
                        {
                            "xml": "<permission android:name=\"com.example.angularcordova.permission.C2D_MESSAGE\" android:protectionLevel=\"signature\" />",
                            "count": 1
                        },
                        {
                            "xml": "<uses-permission android:name=\"com.example.angularcordova.permission.C2D_MESSAGE\" />",
                            "count": 1
                        },
                        {
                            "xml": "<uses-permission android:name=\"com.google.android.c2dm.permission.RECEIVE\" />",
                            "count": 1
                        },
                        {
                            "xml": "<uses-permission android:name=\"android.permission.GET_ACCOUNTS\" />",
                            "count": 1
                        },
                        {
                            "xml": "<uses-permission android:name=\"android.permission.WAKE_LOCK\" />",
                            "count": 1
                        }
                    ],
                    "/manifest/application": [
                        {
                            "xml": "<receiver android:name=\"msopentech.azure.NotificationHub$PushNotificationReceiver\" android:permission=\"com.google.android.c2dm.permission.SEND\"><intent-filter><action android:name=\"com.google.android.c2dm.intent.RECEIVE\" /><category android:name=\"com.example.angularcordova\" /></intent-filter></receiver>",
                            "count": 1
                        }
                    ]
                }
            }
        }
    },
    "installed_plugins": {
        "msopentech.azure.NotificationHub": {
            "PACKAGE_NAME": "com.example.angularcordova"
        }
    },
    "dependent_plugins": {}
}